llama_index/graph_stores/neo4j/__init__.py
llama_index/graph_stores/neo4j/base.py
llama_index/graph_stores/neo4j/cypher_corrector.py
llama_index/graph_stores/neo4j/neo4j_property_graph.py
llama_index_graph_stores_neo4j-0.5.0.dist-info/METADATA
llama_index_graph_stores_neo4j-0.5.0.dist-info/WHEEL
llama_index_graph_stores_neo4j-0.5.0.dist-info/licenses/LICENSE
llama_index_graph_stores_neo4j-0.5.0.dist-info/RECORD
