Metadata-Version: 2.4
Name: llama-index-graph-stores-neo4j
Version: 0.5.0
Summary: llama-index graph stores neo4j integration
Author-email: Your Name <you@example.com>
License-Expression: MIT
License-File: LICENSE
Requires-Python: <4.0,>=3.9
Requires-Dist: llama-index-core<0.14,>=0.13.0
Requires-Dist: neo4j<6,>=5.16.0
